{
  "commit": "c939220c60f4f63a34b7a6cf6dc843023dc09e20",
  "phase": "B-docs",
  "generated_at": "2026-07-19T00:00:00Z",
  "note": "Đối chiếu tuyên bố tài liệu với code. Không phải lỗ hổng bảo mật; là rủi ro tin cậy/review.",
  "findings": [
    {
      "id": "DOC-001",
      "severity": "LOW",
      "category": "docs-mismatch",
      "title": "README có 2 bảng endpoint mâu thuẫn: /auth/signup vs /auth/register",
      "file": "README.md",
      "line": 441,
      "evidence": "Bảng #1 (dòng 275): `POST /auth/signup`. Bảng #2 (dòng 441): `POST /api/v1/auth/register`. Code chỉ có @router.post(\"/signup\") tại src/api/auth_routes.py:295 — KHÔNG có /auth/register.",
      "repro": "grep -n '\"/register\"\\|\"/signup\"' src/api/auth_routes.py",
      "exploit": "N/A — người tích hợp API theo bảng #2 sẽ nhận 404.",
      "fix": "Xoá bảng endpoint trùng, sinh bảng duy nhất từ OpenAPI (/openapi.json).",
      "impact": 2, "likelihood": 3, "effort": "S", "confidence": "confirmed",
      "test_to_prove": "N/A"
    },
    {
      "id": "DOC-002",
      "severity": "LOW",
      "category": "docs-missing",
      "title": "ARCHITECTURE.md là template rỗng chưa điền",
      "file": "ARCHITECTURE.md",
      "line": 3,
      "evidence": "Toàn placeholder: '[Tóm tắt 2-3 câu...]', '[choice]', '[reason]', Database 'Alembic' (dự án dùng Supabase SQL migration, không Alembic).",
      "repro": "cat ARCHITECTURE.md",
      "exploit": "N/A",
      "fix": "Viết lại theo 4 critical path thực tế; hoặc trỏ về docs/architecture.md nếu đó là bản thật.",
      "impact": 2, "likelihood": 3, "effort": "M", "confidence": "confirmed",
      "test_to_prove": "N/A"
    },
    {
      "id": "DOC-003",
      "severity": "MEDIUM",
      "category": "docs-mismatch-security",
      "title": "README tuyên bố frontend auth qua @supabase/ssr; thực tế lưu JWT trong localStorage/sessionStorage",
      "file": "frontend/app/lib/session.ts",
      "line": 14,
      "evidence": "README dòng 95: 'Frontend Auth/SSR: Supabase SSR (@supabase/ssr)'. Thực tế: session.ts đọc/ghi 'mentora-auth-session' bằng window.sessionStorage/localStorage. Không có @supabase/ssr trong package.json; grep supabase trong frontend/ = 0 kết quả.",
      "repro": "grep -rn 'supabase' frontend/app  # 0 hits — package.json không có @supabase/ssr",
      "exploit": "JWT nằm trong localStorage có thể bị đánh cắp qua XSS (khác với httpOnly cookie mà @supabase/ssr dùng). Xem SEC nếu có XSS.",
      "fix": "Sửa README cho đúng; hoặc chuyển sang cookie httpOnly nếu muốn đúng như tuyên bố.",
      "impact": 3, "likelihood": 2, "effort": "M", "confidence": "confirmed",
      "test_to_prove": "N/A",
      "related": ["FE-jwt-localstorage"]
    },
    {
      "id": "DOC-004",
      "severity": "LOW",
      "category": "docs-mismatch",
      "title": "README tuyên bố Zustand cho state; frontend không dùng Zustand",
      "file": "frontend/package.json",
      "line": 15,
      "evidence": "Tech stack (README:94) ghi 'Zustand'. package.json dependencies không có zustand; state dùng React useSyncExternalStore (session.ts) + hooks cục bộ.",
      "repro": "grep -rn 'zustand' frontend/  # 0 hits",
      "exploit": "N/A",
      "fix": "Bỏ Zustand khỏi tech stack hoặc thêm nếu định dùng.",
      "impact": 1, "likelihood": 3, "effort": "S", "confidence": "confirmed",
      "test_to_prove": "N/A"
    },
    {
      "id": "DOC-005",
      "severity": "LOW",
      "category": "docs-mismatch",
      "title": "Tuyên bố Tailwind CSS 4 nhưng postcss plugin rỗng, styling là CSS thủ công",
      "file": "frontend/postcss.config.mjs",
      "line": 1,
      "evidence": "postcss.config.mjs: `const config = { plugins: {} }` (rỗng). globals.css bắt đầu bằng biến CSS thủ công (:root{--bg...}), không thấy `@import \"tailwindcss\"`. @tailwindcss có trong node_modules nhưng không được wire qua postcss.",
      "repro": "cat frontend/postcss.config.mjs; head frontend/app/globals.css",
      "exploit": "N/A",
      "fix": "Xác nhận có thực sự dùng Tailwind không; cập nhật tài liệu cho đúng.",
      "impact": 1, "likelihood": 2, "effort": "S", "confidence": "suspected",
      "test_to_prove": "N/A"
    },
    {
      "id": "DOC-006",
      "severity": "LOW",
      "category": "config-inconsistency",
      "title": "Bất đồng phiên bản Python: requires-python>=3.13 vs Docker 3.11 vs ruff py311",
      "file": "Dockerfile",
      "line": 2,
      "evidence": "pyproject.toml:6 `requires-python = \">=3.13\"`; Dockerfile:2/13 `FROM python:3.11-slim`; ruff.toml:1 `target-version = \"py311\"`. Production chạy 3.11 nhưng khai báo cần 3.13.",
      "repro": "grep requires-python pyproject.toml; grep FROM Dockerfile; grep target-version ruff.toml",
      "exploit": "N/A — nhưng cú pháp/hành vi 3.12+ (vd type params) sẽ hỏng khi build Docker.",
      "fix": "Thống nhất một phiên bản (đề xuất 3.13 khắp nơi, hoặc hạ requires-python xuống 3.11).",
      "impact": 2, "likelihood": 2, "effort": "S", "confidence": "confirmed",
      "test_to_prove": "docker build ."
    },
    {
      "id": "DOC-007",
      "severity": "LOW",
      "category": "config-inconsistency",
      "title": "Hai nguồn dependency lệch nhau (pyproject.toml vs requirements.txt)",
      "file": "requirements.txt",
      "line": 27,
      "evidence": "requirements.txt có psycopg2-binary, pgvector; pyproject.toml KHÔNG có. Dockerfile cài từ requirements.txt, uv sync dùng pyproject → hai môi trường khác nhau.",
      "repro": "diff <(grep -oE '^[a-z0-9-]+' requirements.txt|sort) <(...)",
      "exploit": "N/A",
      "fix": "Chọn một nguồn chân lý (đề xuất pyproject + uv.lock), sinh requirements.txt từ đó.",
      "impact": 2, "likelihood": 2, "effort": "S", "confidence": "confirmed",
      "test_to_prove": "N/A"
    },
    {
      "id": "DOC-008",
      "severity": "LOW",
      "category": "docs-missing",
      "title": "Không có middleware route protection ở frontend (SPA client-only guard)",
      "file": "frontend",
      "line": 0,
      "evidence": "Không tồn tại frontend/middleware.ts. Bảo vệ route chỉ dựa vào session.ts đọc localStorage phía client. Backend vẫn kiểm JWT mỗi request nên dữ liệu không lộ, nhưng route riêng tư có thể 'nháy' trước khi redirect.",
      "repro": "find frontend -name middleware.ts  # trống",
      "exploit": "Truy cập trực tiếp URL riêng tư khi chưa đăng nhập sẽ render khung UI trước khi client redirect; dữ liệu thật vẫn cần token nên không lộ.",
      "fix": "Nếu muốn chặn server-side, cần chuyển token sang cookie + middleware. Với SPA hiện tại, đảm bảo mọi fetch đều gửi token và xử lý 401.",
      "impact": 2, "likelihood": 2, "effort": "M", "confidence": "confirmed",
      "test_to_prove": "N/A"
    },
    {
      "id": "DOC-009",
      "severity": "INFO",
      "category": "docs-match",
      "title": "[POSITIVE] Mục tiêu ZPD 70-75% CÓ được cài đặt thật trong reward",
      "file": "src/services/adaptive/bandit.py",
      "line": 178,
      "evidence": "zpd_reward = 1.0 - 2.0 * abs(expected_success - 0.75) — hàm reward đạt cực đại tại xác suất đúng 0.75, khớp tuyên bố README. bkt.py:66 dùng ngưỡng đúng/sai 0.75.",
      "repro": "grep -n 0.75 src/services/adaptive/bandit.py",
      "exploit": "N/A",
      "fix": "Không cần — ghi nhận là điểm tốt cần giữ khi refactor.",
      "impact": 0, "likelihood": 0, "effort": "S", "confidence": "confirmed",
      "test_to_prove": "tests/... bandit reward peak"
    }
  ]
}
